[
    {
        "positionsCollection":[],
        "parents": {
            "idparents":31,
            "parent1":"Omar",
            "email1":"tanianevin@yahoo.com, oacosta65@yahoo.com",
            "phone1":"(512) 763-9952",
            "parent2":"Tania",
            "email2":"tanianevin@yahoo.com, oacosta65@yahoo.com",
            "phone2":"(512) 534-9018",
            "phone1CanText":true,
            "phone2CanText":true},
        "teamsId": {
            "idteams":5,
            "name":"Austin Angels 12U",
            "level":"12UW"},
        "idplayers":1,
        "nickname":"Toothbrush",
        "number":"43",
        "lastname":"Acosta",
        "firstname":"Darren",
        "bats":"R",
        "throws1":"R",
        "isActive":true
    },
    
    {"positionsCollection":[],"parents":{"idparents":31,"parent1":"Omar","email1":"tanianevin@yahoo.com, oacosta65@yahoo.com","phone1":"(512) 763-9952","parent2":"Tania","email2":"tanianevin@yahoo.com, oacosta65@yahoo.com","phone2":"(512) 534-9018","phone1CanText":true,"phone2CanText":true},"teamsId":{"idteams":4,"name":"Austin Angels 13U White","level":"13UW"},"idplayers":11,"nickname":"Toothpick","number":"22","lastname":"Acosta","firstname":"Damian","bats":"R","throws1":"R","isActive":true},{"positionsCollection":[],"parents":{"idparents":48,"parent1":"Daniel Acosta","email1":"danieljacosta14@yahoo.com","phone1":"(512) 9059378","parent2":"Whitney Kuempel","email2":null,"phone2":"(512) 293-5030","phone1CanText":true,"phone2CanText":true},"teamsId":{"idteams":5,"name":"Austin Angels 12U","level":"12UW"},"idplayers":48,"nickname":"","number":"14","lastname":"Acosta","firstname":"Tyler","bats":"R","throws1":"R","isActive":true},{"positionsCollection":[],"parents":{"idparents":12,"parent1":"Don","email1":"dvadair@sbcglobal.net","phone1":"(512) 296-4692","parent2":"Vicki","email2":"dvadair@sbcglobal.net","phone2":"(512) 296-4238","phone1CanText":true,"phone2CanText":true},"teamsId":{"idteams":1,"name":"Austin Angels 14U","level":"14UR"},"idplayers":33,"nickname":"Kid","number":"32","lastname":"Adair","firstname":"Chase ","bats":"R","throws1":"R","isActive":true},{"positionsCollection":[],"parents":{"idparents":12,"parent1":"Don","email1":"dvadair@sbcglobal.net","phone1":"(512) 296-4692","parent2":"Vicki","email2":"dvadair@sbcglobal.net","phone2":"(512) 296-4238","phone1CanText":true,"phone2CanText":true},"teamsId":{"idteams":7,"name":"Austin Angels 11U","level":"11UW"},"idplayers":2,"nickname":"Nolan Ryan","number":"6","lastname":"Adair","firstname":"Austin","bats":"R","throws1":"R","isActive":true},{"positionsCollection":[],"parents":{"idparents":40,"parent1":"Scott","email1":"scott.aylor@gmail.com","phone1":null,"parent2":"Kathy","email2":null,"phone2":null,"phone1CanText":true,"phone2CanText":true},"teamsId":{"idteams":1,"name":"Austin Angels 14U","level":"14UR"},"idplayers":43,"nickname":"Baby","number":"8","lastname":"Aylor","firstname":"Garrett","bats":"R","throws1":"L","isActive":true},{"positionsCollection":[],"parents":{"idparents":7,"parent1":"Bruce","email1":"Bruce_Bell@Dell.com, starstrk@gmail.com, \npetalpal@austin.rr.com","phone1":"(512) 431-5586","parent2":"Lana","email2":"Bruce_Bell@Dell.com, starstrk@gmail.com, \npetalpal@austin.rr.com","phone2":"(512) 970-9875","phone1CanText":true,"phone2CanText":true},"teamsId":{"idteams":1,"name":"Austin Angels 14U","level":"14UR"},"idplayers":34,"nickname":"4G","number":"33","lastname":"Bell","firstname":"Forrest","bats":"R","throws1":"R","isActive":true},{"positionsCollection":[],"parents":{"idparents":59,"parent1":"todd","email1":"bradleytodd55@yahoo.com","phone1":"(512) 825-8585","parent2":"sharon","email2":null,"phone2":"(860) 630-3681","phone1CanText":true,"phone2CanText":true},"teamsId":{"idteams":4,"name":"Austin Angels 13U White","level":"13UW"},"idplayers":59,"nickname":"","number":"","lastname":"Bradley","firstname":"tanner","bats":"R","throws1":"R","isActive":true},{"positionsCollection":[],"parents":{"idparents":26,"parent1":"Ken","email1":"candy.burge@gmail.com, \n4lburge@sbcglobal.net","phone1":"(512) 848-5664","parent2":"Candy ","email2":"candy.burge@gmail.com, \n4lburge@sbcglobal.net","phone2":"(512) 2940036","phone1CanText":true,"phone2CanText":true},"teamsId":{"idteams":1,"name":"Austin Angels 14U","level":"14UR"},"idplayers":35,"nickname":"D.T.","number":"23","lastname":"Burge","firstname":"Layton","bats":"R","throws1":"R","isActive":true},{"positionsCollection":[],"parents":{"idparents":27,"parent1":"Kevin","email1":"biz_e_sharonoc@yahoo.com, kchervenka@yahoo.com\n","phone1":"(512) 563-0504","parent2":"Sharon","email2":"biz_e_sharonoc@yahoo.com, kchervenka@yahoo.com\n","phone2":"(512) 626-8664","phone1CanText":true,"phone2CanText":true},"teamsId":{"idteams":7,"name":"Austin Angels 11U","level":"11UW"},"idplayers":3,"nickname":"JC","number":"34","lastname":"Chervenka","firstname":"Justin","bats":"R","throws1":"R","isActive":true},{"positionsCollection":[],"parents":{"idparents":49,"parent1":"Stan","email1":"chmurafamily@yahoo.com","phone1":"(301) 6021632","parent2":"Shellie","email2":null,"phone2":"(301) 602-1630","phone1CanText":true,"phone2CanText":true},"teamsId":{"idteams":5,"name":"Austin Angels 12U","level":"12UW"},"idplayers":49,"nickname":"","number":"24","lastname":"Chmura","firstname":"Zachary","bats":"R","throws1":"R","isActive":true},{"positionsCollection":[],"parents":{"idparents":5,"parent1":"Brent ","email1":"bkc3908@gmail.com, april498@gmail.com","phone1":"(512) 745-1205","parent2":"April ","email2":"bkc3908@gmail.com, april498@gmail.com","phone2":"(512) 745-1206","phone1CanText":true,"phone2CanText":true},"teamsId":{"idteams":1,"name":"Austin Angels 14U","level":"14UR"},"idplayers":36,"nickname":"Hook","number":"6","lastname":"Christiansen","firstname":"Collin","bats":"R","throws1":"R","isActive":true},{"positionsCollection":[],"parents":{"idparents":9,"parent1":"Craig ","email1":"shanda.dame@gmail.com, \ncraig.dame.gt7l@statefarm.com","phone1":"(512) 539-6246","parent2":"Shanda ","email2":"shanda.dame@gmail.com, \ncraig.dame.gt7l@statefarm.com","phone2":"(469) 734-8226","phone1CanText":true,"phone2CanText":true},"teamsId":{"idteams":3,"name":"Austin Angels 13U Red","level":"13UR"},"idplayers":22,"nickname":"Pepper","number":"34","lastname":"Dame","firstname":"Parker","bats":"R","throws1":"R","isActive":true},{"positionsCollection":[],"parents":{"idparents":20,"parent1":"Jack","email1":"tarheel2022@gmail.com, \ndilullo@us.ibm.com, irishleener@gmail.com \n\n","phone1":"(512) 913-9950","parent2":"Eileen","email2":"tarheel2022@gmail.com, \ndilullo@us.ibm.com, irishleener@gmail.com \n\n","phone2":"(512) 963-0001","phone1CanText":true,"phone2CanText":true},"teamsId":{"idteams":3,"name":"Austin Angels 13U Red","level":"13UR"},"idplayers":23,"nickname":"Uncle Pete","number":"51","lastname":"DiLullo","firstname":"Patrick","bats":"R","throws1":"R","isActive":true},{"positionsCollection":[],"parents":{"idparents":56,"parent1":"Darrell Fletcher","email1":"dafletch@sbcglobal.net, barbaralfletcher@sbcglobal.net","phone1":null,"parent2":"Barbara Fletcher","email2":null,"phone2":null,"phone1CanText":true,"phone2CanText":true},"teamsId":{"idteams":3,"name":"Austin Angels 13U Red","level":"13UR"},"idplayers":56,"nickname":"","number":"22","lastname":"Fletcher","firstname":"Alex ","bats":"R","throws1":"R","isActive":true},{"positionsCollection":[],"parents":{"idparents":6,"parent1":"Brian","email1":"gavra.flood@twc.state.tx.us, bgflood@kpmg.com, \ngflood@austin.rr.com","phone1":"(512) 506-8720","parent2":"Gavra","email2":"gavra.flood@twc.state.tx.us, bgflood@kpmg.com, \ngflood@austin.rr.com","phone2":"(512) 506-8720","phone1CanText":true,"phone2CanText":true},"teamsId":{"idteams":7,"name":"Austin Angels 11U","level":"11UW"},"idplayers":4,"nickname":"Mace","number":"12","lastname":"Flood","firstname":"Mason","bats":"R","throws1":"R","isActive":true},{"positionsCollection":[],"parents":{"idparents":60,"parent1":"John","email1":"tlfullerton@yahoo.com","phone1":"(512) 864-1353","parent2":"Tanya","email2":null,"phone2":"(512) 284-4685","phone1CanText":true,"phone2CanText":true},"teamsId":{"idteams":4,"name":"Austin Angels 13U White","level":"13UW"},"idplayers":60,"nickname":"","number":"","lastname":"Fullerton","firstname":"Ryan","bats":"R","throws1":"R","isActive":true},{"positionsCollection":[],"parents":{"idparents":63,"parent1":"n/a","email1":"triciaconner@austin.rr.com, seanphillips7@yahoo.com","phone1":"","parent2":"Tricia Conner","email2":null,"phone2":"(512) 470-6504","phone1CanText":true,"phone2CanText":true},"teamsId":{"idteams":1,"name":"Austin Angels 14U","level":"14UR"},"idplayers":63,"nickname":"","number":"12","lastname":"Gibbs","firstname":"Conner","bats":"R","throws1":"R","isActive":true},{"positionsCollection":[],"parents":{"idparents":44,"parent1":"Brent Gilmore ","email1":"bagilmore@aol.com","phone1":"(512) 296-4270","parent2":"Aimee Gillmore ","email2":null,"phone2":"(512) 680-0811","phone1CanText":true,"phone2CanText":true},"teamsId":{"idteams":7,"name":"Austin Angels 11U","level":"11UW"},"idplayers":44,"nickname":"","number":"","lastname":"Gilmore","firstname":"Reese ","bats":"R","throws1":"R","isActive":true},{"positionsCollection":[],"parents":{"idparents":50,"parent1":"Greg","email1":"greg.greinke@sbcglobal.net, olie63@yahoo.com","phone1":"(512) 426-2934","parent2":"Wendy ","email2":null,"phone2":"(512) 246-2934","phone1CanText":true,"phone2CanText":true},"teamsId":{"idteams":5,"name":"Austin Angels 12U","level":"12UW"},"idplayers":50,"nickname":"","number":"6","lastname":"Greinke ","firstname":"Grayson ","bats":"R","throws1":"R","isActive":true},{"positionsCollection":[],"parents":{"idparents":1,"parent1":null,"email1":"grones-kelly@aramark.com","phone1":null,"parent2":"Kelly Grones","email2":"grones-kelly@aramark.com","phone2":"(361) 649-9597","phone1CanText":true,"phone2CanText":true},"teamsId":{"idteams":4,"name":"Austin Angels 13U White","level":"13UW"},"idplayers":14,"nickname":"Gronzie","number":"13","lastname":"Grones","firstname":"Allen","bats":"R","throws1":"R","isActive":true},{"positionsCollection":[],"parents":{"idparents":21,"parent1":"James Ubbins ","email1":"joygroves20@yahoo.com,\nJMoreland@seton.org","phone1":null,"parent2":"Joy Groves","email2":"joygroves20@yahoo.com,\nJMoreland@seton.org","phone2":"(512) 517-1500","phone1CanText":true,"phone2CanText":true},"teamsId":{"idteams":1,"name":"Austin Angels 14U","level":"14UR"},"idplayers":24,"nickname":"Big E","number":"21","lastname":"Groves","firstname":"Ian","bats":"R","throws1":"R","isActive":true},{"positionsCollection":[],"parents":{"idparents":24,"parent1":"John ","email1":"cahanrahan2001@yahoo.com, cahanrahan2001@yahoo.com","phone1":null,"parent2":"Christa","email2":"cahanrahan2001@yahoo.com, cahanrahan2001@yahoo.com","phone2":null,"phone1CanText":true,"phone2CanText":true},"teamsId":{"idteams":4,"name":"Austin Angels 13U White","level":"13UW"},"idplayers":15,"nickname":"Hammer","number":"15","lastname":"Hanrahan","firstname":"Patrick","bats":"R","throws1":"R","isActive":true},{"positionsCollection":[],"parents":{"idparents":64,"parent1":"N/A. Grandparents: Larry & Barbara Heinzke","email1":"bheinzke@sbcglobal.net, kellyf.ramsey@gmail.com, theinzke@gmail.com\n","phone1":"(512) 281-5468","parent2":"Tera Heinzke","email2":null,"phone2":"(512) 281-5468","phone1CanText":true,"phone2CanText":true},"teamsId":{"idteams":1,"name":"Austin Angels 14U","level":"14UR"},"idplayers":64,"nickname":"","number":"25","lastname":"Heinzke","firstname":"Noah","bats":"R","throws1":"R","isActive":true},{"positionsCollection":[],"parents":{"idparents":51,"parent1":"Joe Jackson","email1":"jojacktx@yahoo.com","phone1":"(512) 565-3634","parent2":"Michelle Jackson","email2":null,"phone2":"(512) 565-3634","phone1CanText":true,"phone2CanText":true},"teamsId":{"idteams":5,"name":"Austin Angels 12U","level":"12UW"},"idplayers":51,"nickname":"","number":"5","lastname":"Jackson","firstname":"Kyle","bats":"R","throws1":"R","isActive":true},{"positionsCollection":[],"parents":{"idparents":57,"parent1":"George Negrete","email1":"njaimes33@gmail.com, georgenegrete.2009@gmail.com","phone1":"","parent2":"Nicole Jaimes","email2":null,"phone2":"","phone1CanText":true,"phone2CanText":true},"teamsId":{"idteams":3,"name":"Austin Angels 13U Red","level":"13UR"},"idplayers":57,"nickname":"","number":"33","lastname":"Jaimes","firstname":"Jai","bats":"R","throws1":"R","isActive":true},{"positionsCollection":[],"parents":{"idparents":25,"parent1":"Julian ","email1":"julian.jasmin@us.army.mil, \nstella.jasmin@killeenisd.org","phone1":"(254) 368-9827","parent2":"Stella","email2":"julian.jasmin@us.army.mil, \nstella.jasmin@killeenisd.org","phone2":"(512) 566-0048","phone1CanText":true,"phone2CanText":true},"teamsId":{"idteams":3,"name":"Austin Angels 13U Red","level":"13UR"},"idplayers":25,"nickname":"Pony","number":"11","lastname":"Jasmin","firstname":"Julian","bats":"R","throws1":"R","isActive":true},{"positionsCollection":[],"parents":{"idparents":52,"parent1":"Jeff Johns","email1":"jdjohns71@yahoo.com","phone1":"(512) 576-5766","parent2":"Monica Reyna","email2":null,"phone2":"(512) 579-6431","phone1CanText":true,"phone2CanText":true},"teamsId":{"idteams":5,"name":"Austin Angels 12U","level":"12UW"},"idplayers":52,"nickname":"","number":"1","lastname":"Johns","firstname":"Jawuan","bats":"R","throws1":"R","isActive":true},{"positionsCollection":[],"parents":{"idparents":2,"parent1":"Alan ","email1":"alan_kelch@dell.com, ackelch@gmail.com,\nsherry_kelch@dell.com","phone1":"(512) 506-0584","parent2":"Sherry ","email2":"alan_kelch@dell.com, ackelch@gmail.com,\nsherry_kelch@dell.com","phone2":"(512) 818-1572","phone1CanText":true,"phone2CanText":true},"teamsId":{"idteams":3,"name":"Austin Angels 13U Red","level":"13UR"},"idplayers":17,"nickname":"Bigfoot","number":"14","lastname":"Kelch","firstname":"Cody","bats":"R","throws1":"R","isActive":true},{"positionsCollection":[{"idpositions":1,"position":"2B"}],"parents":{"idparents":19,"parent1":"Glenn","email1":"grk@corelogic.com","phone1":"(512) 657-4117","parent2":"Teresa","email2":"ter.kron@yahoo.com","phone2":"(512) 705-6639","phone1CanText":true,"phone2CanText":true},"teamsId":{"idteams":3,"name":"Austin Angels 13U Red","level":"13UR"},"idplayers":26,"nickname":"Miguel","number":"32","lastname":"Kronschnabl","firstname":"Michael","bats":"R","throws1":"R","isActive":true},{"positionsCollection":[],"parents":{"idparents":36,"parent1":"Scott","email1":"slittle9@austin.rr.com, slittle@corelogic.com","phone1":"(512) 297-6680","parent2":"Sharon ","email2":"slittle9@austin.rr.com, slittle@corelogic.com","phone2":"(512) 750-9051","phone1CanText":true,"phone2CanText":true},"teamsId":{"idteams":1,"name":"Austin Angels 14U","level":"14UR"},"idplayers":40,"nickname":"Coach","number":"00","lastname":"Little ","firstname":"Aaron","bats":"R","throws1":"R","isActive":true},{"positionsCollection":[],"parents":{"idparents":46,"parent1":null,"email1":"joe.mat@sbcglobal.net, christa.matamoros@sbcglobal.net\n","phone1":null,"parent2":null,"email2":null,"phone2":null,"phone1CanText":true,"phone2CanText":true},"teamsId":{"idteams":7,"name":"Austin Angels 11U","level":"11UW"},"idplayers":46,"nickname":"","number":"7","lastname":"Matamoros","firstname":"Anthony ","bats":"R","throws1":"R","isActive":true},{"positionsCollection":[],"parents":{"idparents":8,"parent1":"Charlie Brady","email1":"bradybunch1814@att.net","phone1":"(512) 914-3633","parent2":"Lori Brady","email2":"bradybunch1814@att.net","phone2":"(512) 569-6080","phone1CanText":true,"phone2CanText":true},"teamsId":{"idteams":4,"name":"Austin Angels 13U White","level":"13UW"},"idplayers":27,"nickname":"Nacho","number":"9","lastname":"McGathy","firstname":"Garrett","bats":"R","throws1":"L","isActive":true},{"positionsCollection":[],"parents":{"idparents":28,"parent1":"Mark","email1":"reneemcm@msn.com","phone1":"(512) 658-9360","parent2":"Renee","email2":"reneemcm@msn.com","phone2":"(512) 658-9362","phone1CanText":true,"phone2CanText":true},"teamsId":{"idteams":4,"name":"Austin Angels 13U White","level":"13UW"},"idplayers":18,"nickname":"Red","number":"8","lastname":"McMillan","firstname":"Evan","bats":"R","throws1":"R","isActive":true},{"positionsCollection":[],"parents":{"idparents":47,"parent1":"Jeff ","email1":"jefeneely@gmail.com","phone1":"(512) 300-7259","parent2":"Janelle","email2":null,"phone2":"(512) 364-3939","phone1CanText":true,"phone2CanText":true},"teamsId":{"idteams":7,"name":"Austin Angels 11U","level":"11UW"},"idplayers":47,"nickname":"","number":"","lastname":"Neely ","firstname":"Benjamin ","bats":"R","throws1":"R","isActive":true},{"positionsCollection":[],"parents":{"idparents":53,"parent1":"John Pena","email1":"johnrpena@earthlink.net, mjacktx@gmail.com","phone1":"(512) 789-2055","parent2":"Colette Pena","email2":null,"phone2":"(512) 636-6530","phone1CanText":true,"phone2CanText":true},"teamsId":{"idteams":5,"name":"Austin Angels 12U","level":"12UW"},"idplayers":53,"nickname":"","number":"13","lastname":"Pena","firstname":"Nicholas","bats":"R","throws1":"R","isActive":true},{"positionsCollection":[],"parents":{"idparents":3,"parent1":"Bit","email1":"rambo0117@yahoo.com, Bit_Rambusch@Dell.com,\ntrambusch@gmail.com, jesuschick146@yahoo.com","phone1":"(512) 632-2871","parent2":"Lori","email2":"rambo0117@yahoo.com, Bit_Rambusch@Dell.com,\ntrambusch@gmail.com, jesuschick146@yahoo.com","phone2":"(512) 963-9614","phone1CanText":true,"phone2CanText":true},"teamsId":{"idteams":3,"name":"Austin Angels 13U Red","level":"13UR"},"idplayers":28,"nickname":"Velcro","number":"00","lastname":"Rambusch","firstname":"Blake","bats":"R","throws1":"R","isActive":true},{"positionsCollection":[],"parents":{"idparents":45,"parent1":"Ken Ramsey ","email1":"ken.cpesupv@gmail.com, kellyf.ramsey@gmail.com","phone1":"(832) 746-3076","parent2":"Kelly Ramsey","email2":null,"phone2":"(512) 433-9648","phone1CanText":true,"phone2CanText":true},"teamsId":{"idteams":7,"name":"Austin Angels 11U","level":"11UW"},"idplayers":45,"nickname":"","number":"","lastname":"Ramsey ","firstname":"Ryan ","bats":"R","throws1":"R","isActive":true},{"positionsCollection":[],"parents":{"idparents":54,"parent1":"Jeff Johns (stepdad)","email1":"macareyna32@yahoo.com","phone1":"(512) 576-5766","parent2":"Monica Reyna","email2":null,"phone2":"(512) 579-6431","phone1CanText":true,"phone2CanText":true},"teamsId":{"idteams":5,"name":"Austin Angels 12U","level":"12UW"},"idplayers":54,"nickname":"","number":"11","lastname":"Reyna","firstname":"Jonathon","bats":"R","throws1":"R","isActive":true},{"positionsCollection":[],"parents":{"idparents":55,"parent1":"Steve Rosengren","email1":"ser@us.ibm.com, krosengr@us.ibm.com","phone1":"(512) 633-6876","parent2":"Karen","email2":null,"phone2":"(512) 426-9706","phone1CanText":true,"phone2CanText":true},"teamsId":{"idteams":5,"name":"Austin Angels 12U","level":"12UW"},"idplayers":55,"nickname":"","number":"4","lastname":"Rosengren","firstname":"Kevin ","bats":"R","throws1":"R","isActive":true},{"positionsCollection":[],"parents":{"idparents":38,"parent1":"Todd","email1":"alicia419@att.net, todd_russell@cerilliant.com","phone1":"(512) 785-3267","parent2":"Alicia","email2":"alicia419@att.net, todd_russell@cerilliant.com","phone2":"(512) 964-3914","phone1CanText":true,"phone2CanText":true},"teamsId":{"idteams":7,"name":"Austin Angels 11U","level":"11UW"},"idplayers":6,"nickname":"Money","number":"00","lastname":"Russell","firstname":"Will","bats":"R","throws1":"R","isActive":true},{"positionsCollection":[],"parents":{"idparents":22,"parent1":"Jerry","email1":"jdsal99@gmail.com, \nevesal99@gmail.com, jerry_salgado@dell.com","phone1":"(512) 422-9391","parent2":"Evelyn","email2":"jdsal99@gmail.com, \nevesal99@gmail.com, jerry_salgado@dell.com","phone2":"(512) 577-1380","phone1CanText":true,"phone2CanText":true},"teamsId":{"idteams":3,"name":"Austin Angels 13U Red","level":"13UR"},"idplayers":29,"nickname":"8:27","number":"46","lastname":"Salgado","firstname":"Beck","bats":"R","throws1":"R","isActive":true},{"positionsCollection":[],"parents":{"idparents":15,"parent1":"Edgar","email1":"edgar73saucedo@yahoo.com, kimbry_Saucedo@yahoo.com","phone1":"(512) 657-4628","parent2":"Kimbry ","email2":"edgar73saucedo@yahoo.com, kimbry_Saucedo@yahoo.com","phone2":"(512) 438-9580","phone1CanText":true,"phone2CanText":true},"teamsId":{"idteams":4,"name":"Austin Angels 13U White","level":"13UW"},"idplayers":20,"nickname":"Earthworm","number":"17","lastname":"Saucedo","firstname":"Christian","bats":"R","throws1":"R","isActive":true},{"positionsCollection":[],"parents":{"idparents":58,"parent1":"STEVE","email1":"CINDYSAVARESE@YAHOO.COM","phone1":"(225) 235-0695","parent2":"CINDY","email2":null,"phone2":"(225) 324-5797","phone1CanText":true,"phone2CanText":true},"teamsId":{"idteams":3,"name":"Austin Angels 13U Red","level":"13UR"},"idplayers":58,"nickname":"","number":"16","lastname":"Savarese","firstname":"Hunter ","bats":"R","throws1":"R","isActive":true},{"positionsCollection":[],"parents":{"idparents":4,"parent1":"Bobby ","email1":"bobevankc@gmail.com, whimsigirl@gmail.com","phone1":"(512) 809-1023","parent2":"Evan ","email2":"bobevankc@gmail.com, whimsigirl@gmail.com","phone2":"(512) 415-4491","phone1CanText":true,"phone2CanText":true},"teamsId":{"idteams":4,"name":"Austin Angels 13U White","level":"13UW"},"idplayers":21,"nickname":"Slim Shady","number":"5","lastname":"Shaw","firstname":"Joey","bats":"R","throws1":"R","isActive":true},{"positionsCollection":[],"parents":{"idparents":61,"parent1":"Jim","email1":"Tres.mujeres@yahoo.com, slayterx5@yahoo.com","phone1":"(512) 468-0785","parent2":"Nelda","email2":null,"phone2":"(512) 635-8631","phone1CanText":true,"phone2CanText":true},"teamsId":{"idteams":4,"name":"Austin Angels 13U White","level":"13UW"},"idplayers":61,"nickname":"","number":"","lastname":"Slayter","firstname":"Jameson","bats":"R","throws1":"R","isActive":true},{"positionsCollection":[],"parents":{"idparents":65,"parent1":"Chad Svoboda","email1":"csvoboda22@gmail.com, jsvoboda22@gmail.com","phone1":null,"parent2":"Joan Svoboda","email2":null,"phone2":null,"phone1CanText":true,"phone2CanText":true},"teamsId":{"idteams":1,"name":"Austin Angels 14U","level":"14UR"},"idplayers":65,"nickname":"","number":"22","lastname":"Svoboda","firstname":"Steven","bats":"R","throws1":"R","isActive":true},{"positionsCollection":[],"parents":{"idparents":10,"parent1":"Daniel ","email1":"joyce.tamez@leanderisd.org, \ndaniel.tamez@pflugervilleisd.net","phone1":"(512) 784-8078","parent2":"Joyce ","email2":"joyce.tamez@leanderisd.org, \ndaniel.tamez@pflugervilleisd.net","phone2":"(512) 296-6260","phone1CanText":true,"phone2CanText":true},"teamsId":{"idteams":5,"name":"Austin Angels 12U","level":"12UW"},"idplayers":30,"nickname":"","number":"22","lastname":"Tamez","firstname":"Damon","bats":"R","throws1":"R","isActive":true},{"positionsCollection":[],"parents":{"idparents":33,"parent1":"Pete","email1":"sunshine82600@yahoo.com","phone1":"(585) 402-2472\n(512) 992-0514(hm)","parent2":"Rosie","email2":"sunshine82600@yahoo.com","phone2":"(585) 813-5134","phone1CanText":true,"phone2CanText":true},"teamsId":{"idteams":5,"name":"Austin Angels 12U","level":"12UW"},"idplayers":8,"nickname":"Peter T","number":"7","lastname":"Titus","firstname":"Peter","bats":"R","throws1":"R","isActive":true},{"positionsCollection":[],"parents":{"idparents":62,"parent1":"Rob","email1":"rwalters@contractorsinc.com, Tiffany_genee@hotmail.com","phone1":"(512) 801-0211","parent2":"jennifer","email2":null,"phone2":"","phone1CanText":true,"phone2CanText":true},"teamsId":{"idteams":4,"name":"Austin Angels 13U White","level":"13UW"},"idplayers":62,"nickname":"","number":"","lastname":"Walters","firstname":"Tyler","bats":"R","throws1":"R","isActive":true},{"positionsCollection":[],"parents":{"idparents":66,"parent1":"Brian Williams","email1":"donicalyn@yahoo.com, dwilliams@netcotitle.com","phone1":"(512) 635-7105","parent2":"Donica Williams","email2":null,"phone2":"(512) 635-5435","phone1CanText":true,"phone2CanText":true},"teamsId":{"idteams":1,"name":"Austin Angels 14U","level":"14UR"},"idplayers":66,"nickname":"","number":"3","lastname":"Williams","firstname":"Chad","bats":"R","throws1":"R","isActive":true},{"positionsCollection":[],"parents":{"idparents":18,"parent1":"Eric Worden","email1":"worden1010@yahoo.com","phone1":"(512) 801-3464","parent2":"Sonya","email2":"worden1010@yahoo.com","phone2":"(512) 667-3057","phone1CanText":true,"phone2CanText":true},"teamsId":{"idteams":3,"name":"Austin Angels 13U Red","level":"13UR"},"idplayers":32,"nickname":"","number":"10","lastname":"Worden","firstname":"Eric","bats":"R","throws1":"R","isActive":true},{"positionsCollection":[],"parents":{"idparents":41,"parent1":"Brandon (Brother)","email1":null,"phone1":"(512) 801-8013","parent2":null,"email2":null,"phone2":null,"phone1CanText":true,"phone2CanText":true},"teamsId":{"idteams":7,"name":"Austin Angels 11U","level":"11UW"},"idplayers":10,"nickname":"A & W","number":"51","lastname":"Worden (Batboy)","firstname":"Alec","bats":"R","throws1":"R","isActive":true},{"positionsCollection":[],"parents":{"idparents":30,"parent1":"Nathan Yarbrough","email1":"Tiffany_genee@hotmail.com","phone1":"(214) 679-6364","parent2":"Tiffany Walters","email2":"Tiffany_genee@hotmail.com","phone2":"(512) 563-5551","phone1CanText":true,"phone2CanText":true},"teamsId":{"idteams":7,"name":"Austin Angels 11U","level":"11UW"},"idplayers":9,"nickname":"Ri Ri","number":"13","lastname":"Yarbrough","firstname":"Riley","bats":"R","throws1":"R","isActive":true},{"positionsCollection":[],"parents":{"idparents":11,"parent1":"David ","email1":"toni.zapata@ni.com, austinangelsbaseball@yahoo.com","phone1":"(512) 424-9977","parent2":"Toni ","email2":"toni.zapata@ni.com, austinangelsbaseball@yahoo.com","phone2":"(512) 635-3119","phone1CanText":true,"phone2CanText":true},"teamsId":{"idteams":3,"name":"Austin Angels 13U Red","level":"13UR"},"idplayers":41,"nickname":"Bug","number":"30","lastname":"Zapata","firstname":"Dillon ","bats":"R","throws1":"R","isActive":true}]